{
  "groups": [
    {
      "name": "",
      "type": "com.ant.app.config.AppProperties",
      "sourceType": "com.ant.app.config.AppProperties"
    }
  ],
  "properties": [
    {
      "name": "app-chrome-path",
      "type": "java.lang.String",
      "sourceType": "com.ant.app.config.AppProperties"
    },
    {
      "name": "app-phantom-path",
      "type": "java.lang.String",
      "sourceType": "com.ant.app.config.AppProperties"
    },
    {
      "name": "app-src-hindu-url",
      "type": "java.lang.String",
      "sourceType": "com.ant.app.config.AppProperties"
    },
    {
      "name": "app-src-toi-url",
      "type": "java.lang.String",
      "sourceType": "com.ant.app.config.AppProperties"
    },
    {
      "name": "hindu-css-selectors",
      "type": "java.util.List<java.lang.String>",
      "sourceType": "com.ant.app.config.AppProperties"
    },
    {
      "name": "toi-css-selectors",
      "type": "java.util.List<java.lang.String>",
      "sourceType": "com.ant.app.config.AppProperties"
    },
    {
      "name": "web-driver-param",
      "type": "java.lang.String",
      "sourceType": "com.ant.app.config.AppProperties"
    }
  ],
  "hints": []
}